{
	"_id": "mU68L9v7wqoDPOPK",
	"_key": "!items!mU68L9v7wqoDPOPK",
	"effects": [
	],
	"folder": null,
	"img": "systems/D35E/icons/powers/discipline/tel.png",
	"name": "Mind Switch, True",
	"system": {
		"ability": {
			"attack": "",
			"critMult": 2,
			"critRange": 20,
			"damage": "",
			"damageMult": 1,
			"twoHandedOnly": false,
			"vsTouchAc": false
		},
		"actionType": "other",
		"activation": {
			"cost": 1,
			"type": "minute"
		},
		"atWill": false,
		"attack": {
			"parts": [
			]
		},
		"attackBonus": "",
		"attackCountFormula": "",
		"attackNotes": "",
		"attackParts": [
		],
		"autoscaleAttackParts": "",
		"baseCl": "0",
		"castTime": "",
		"clOffset": 0,
		"classSource": "",
		"components": {
			"divineFocus": 0,
			"focus": false,
			"material": false,
			"somatic": false,
			"value": "",
			"verbal": false
		},
		"conditionals": [
		],
		"createdBy": "",
		"critConfirmBonus": "",
		"customAttributes": {
		},
		"customAttributesLocked": false,
		"customTag": "",
		"damage": {
			"alternativeParts": [
			],
			"parts": [
			]
		},
		"description": {
			"chat": "",
			"unidentified": "",
			"value": "<div class=\"spell-description\">\n  <p>\n      <strong>Psionic Discipline:</strong>&nbsp;telepathy&nbsp;[mind-affecting];\n    <br>\n    <strong>Level:</strong>&nbsp;Telepath 9;\n    \n    \n    \n    \n    <br>\n    \n    \n      <strong>Manifesting Time:</strong>&nbsp;1 minute<br>\n    <strong>Range:</strong>&nbsp;touch<br>\n    \n    <strong>Target:</strong>&nbsp;living creature touched<br>\n    \n    <strong>Duration:</strong>&nbsp;Instantaneous\n<br>\n    <strong>Power Points/Spell Points Cost:</strong>&nbsp;17<br>\n        <strong>Saving Throw:</strong>&nbsp;Will negates; see text\n\n        <br>\n        <strong>Power Resistance:</strong>&nbsp;no<br>\n  </p>\n  <h2>Description</h2>\n  \n\n<p>As <i>mind switch, </i>except as noted here. You permanently exchange bodies with the subject. Since this power’s duration is instantaneous, you cannot be forced to return to your natural body by means of <i>dispel psionics, </i>an <i>antimagic field, </i>or a similar effect. If the subject’s body dies while you are in it, you are dead. The subject immediately loses one level, but otherwise survives the experience in your natural body. If your natural body dies while the subject is in it, you immediately lose one level, but you likewise survive the experience in your new body.\n</p><p>Your “natural” body is always considered to be the last one you switched out of. If you exchange bodies with a chain of multiple subjects, you need worry only about the welfare of the last body you switched with. In other words, if your mind is expelled from your current body, your mind returns to the last body you switched with, not to your original body. Similarly, if your original body dies but you have since switched minds with a second subject, you take no penalty. You lose a level only if the body you inhabited immediately prior to your current body is killed.\n</p><p><i>XP Cost: </i>10,000 XP.\n</p>\n<hr/>\n\n\n\n</div>\n"
		},
		"display": "",
		"duration": {
			"units": "",
			"value": null
		},
		"effectNotes": "",
		"epic": "",
		"favorite": false,
		"formula": "",
		"identifiedName": "Mind Switch, True",
		"index": {
			"subType": null,
			"uniqueId": ""
		},
		"isDomainSpell": false,
		"isPower": true,
		"isSpellSpontaneousReplacement": false,
		"learnedAt": {
			"bloodline": [
			],
			"class": [
				[
					"Telepath",
					9
				]
			],
			"domain": [
			],
			"elementalSchool": [
			],
			"subDomain": [
			]
		},
		"level": 9,
		"linkId": "",
		"linkImported": false,
		"linkSourceId": "",
		"linkSourceName": "",
		"linkedChargeItem": {
			"id": null,
			"img": null,
			"name": null
		},
		"materials": {
			"consumed": {
				"_deprecated": true,
				"value": false
			},
			"focus": "",
			"value": ""
		},
		"maxDamageDice": 0,
		"maxDamageDiceFormula": "",
		"measureTemplate": {
			"customColor": "",
			"customTexture": "",
			"overrideColor": false,
			"overrideTexture": false,
			"size": 0,
			"type": ""
		},
		"metamagicFeats": {
			"empowered": false,
			"enhanced": false,
			"enhancedHalf": false,
			"enlarged": false,
			"intensified": false,
			"maximized": false,
			"widened": false
		},
		"nameFormula": "",
		"nameFromFormula": false,
		"originId": "",
		"originPack": "",
		"originVersion": 99,
		"possibleUpdate": false,
		"powerPointsCost": 17,
		"pr": true,
		"preparation": {
			"autoDeductCharges": true,
			"maxAmount": 0,
			"mode": "prepared",
			"preparedAmount": 0
		},
		"psionic": "",
		"range": {
			"long": null,
			"units": "touch",
			"value": null
		},
		"recharge": {
			"current": 0,
			"enabled": false,
			"formula": ""
		},
		"requiresPsionicFocus": false,
		"rollTableDraw": {
			"formula": "",
			"id": "",
			"name": "",
			"pack": ""
		},
		"save": {
			"ability": "",
			"dc": "0",
			"dcAutoAbility": "",
			"dcAutoType": "",
			"description": "Will negates; see text\n",
			"originVersion": 97,
			"type": ""
		},
		"school": "tel",
		"shortDescription": "\n\n<p>As <i>mind switch, </i>except as noted here. You permanently exchange bodies with the subject. Since this power’s duration is instantaneous, you cannot be forced to return to your natural body by means of <i>dispel psionics, </i>an <i>antimagic field, </i>or a similar effect. If the subject’s body dies while you are in it, you are dead. The subject immediately loses one level, but otherwise survives the experience in your natural body. If your natural body dies while the subject is in it, you immediately lose one level, but you likewise survive the experience in your new body.\n</p><p>Your “natural” body is always considered to be the last one you switched out of. If you exchange bodies with a chain of multiple subjects, you need worry only about the welfare of the last body you switched with. In other words, if your mind is expelled from your current body, your mind returns to the last body you switched with, not to your original body. Similarly, if your original body dies but you have since switched minds with a second subject, you take no penalty. You lose a level only if the body you inhabited immediately prior to your current body is killed.\n</p><p><i>XP Cost: </i>10,000 XP.\n</p>\n<hr/>\n\n\n",
		"showInQuickbar": false,
		"slOffset": 0,
		"snip": "A permanent brain swap.",
		"source": "",
		"specialActions": [
		],
		"specialId": null,
		"specialPrepared": false,
		"spellArea": "",
		"spellDuration": "Instantaneous\n",
		"spellEffect": "",
		"spellType": {
			"_deprecated": true,
			"value": ""
		},
		"spellbook": "primary",
		"sr": false,
		"subschool": "",
		"summon": [
		],
		"tags": [
		],
		"target": {
			"value": "living creature touched"
		},
		"types": "mind-affecting",
		"uniqueId": "",
		"userNonRemovable": false,
		"uses": {
			"allowMultipleUses": false,
			"autoDeductCharges": true,
			"canBeLinked": false,
			"chargesPerUse": 1,
			"isResource": false,
			"max": 0,
			"maxFormula": "",
			"maxPerUse": null,
			"maxPerUseFormula": "",
			"per": "",
			"rechargeFormula": null,
			"value": 0
		}
	},
	"type": "spell"
}
